kf_sdk/__init__.py
kf_sdk/api_client.py
kf_sdk/api_response.py
kf_sdk/configuration.py
kf_sdk/exceptions.py
kf_sdk/py.typed
kf_sdk/rest.py
kf_sdk/api/__init__.py
kf_sdk/api/dataset_management_api.py
kf_sdk/api/session_management_api.py
kf_sdk/models/__init__.py
kf_sdk/models/configuration_details.py
kf_sdk/models/dataset_details.py
kf_sdk/models/dataset_version.py
kf_sdk/models/http_validation_error.py
kf_sdk/models/location_inner.py
kf_sdk/models/new_configuration.py
kf_sdk/models/new_session.py
kf_sdk/models/organization_details.py
kf_sdk/models/session_management_api.py
kf_sdk/models/user_details.py
kf_sdk/models/user_type_details.py
kf_sdk/models/validation_error.py
kf_sdk-1.0.0.dist-info/LICENSE.md
kf_sdk-1.0.0.dist-info/METADATA
kf_sdk-1.0.0.dist-info/WHEEL
kf_sdk-1.0.0.dist-info/top_level.txt
kf_sdk-1.0.0.dist-info/RECORD
