Metadata-Version: 2.1
Name: kf_sdk
Version: 1.0.0
Summary: FastAPI
Home-page: https://github.com/nsu-ai/kappa
Author: Kappa group from A.I. Center of NSU
Author-email: "Kappa Group from A.I. center of NSU" <ai@nsu.ru>
License: BSD 3-Clause License
Project-URL: Homepage, https://github.com/nsu-ai/kappa
Project-URL: Issues, https://github.com/nsu-ai/kappa/issues
Project-URL: Repository, https://github.com/nsu-ai/kappa.git
Keywords: Kappa,Datasets Management,FastAPI
Classifier: Programming Language :: Python :: 3
Classifier: Operating System :: OS Independent
License-File: LICENSE.md
